<?xml version="1.0" encoding="UTF-8"?>
<!DOCTYPE suite SYSTEM "https://testng.org/testng-1.0.dtd">
<suite name="Suite" parallel="tests">
	<test thread-count="5" name="SalesForceLogin">
		<parameter name="browserName" value="chrome"></parameter>
		<parameter name="url" value="https://login.salesforce.com/"></parameter>
		<parameter name="userName" value="batch03@codegator.us.qa"></parameter>
		<parameter name="passWord" value="Pa55word"></parameter>
		<parameter name="name" value="Fahim"></parameter>
		<parameter name="type" value="Customer - Channel"></parameter>
		<classes>
			<class name="seleniumTestNG.TestNg_SalesForceLogin"></class>
    	</classes>
	</test> <!-- Test -->

	<test thread-count="5" name="SalesForce">
    <classes>
      <class name="seleniumTestNG.Selenium_Day1_Example"/>
    </classes>
  </test> <!-- SalesForce -->
</suite> <!-- Suite -->
